MANIFEST.in
README.rst
setup.py
wccqcc/README.md
wccqcc/__init__.py
wccqcc/getpage.py
wccqcc/wccqcc_combasic.py
wccqcc/wccqcc_combasic_process_version.py
wccqcc/wccqcc_combasic_threading_version.py
wccqcc/wccqcc_expander.py
wccqcc.egg-info/PKG-INFO
wccqcc.egg-info/SOURCES.txt
wccqcc.egg-info/dependency_links.txt
wccqcc.egg-info/requires.txt
wccqcc.egg-info/top_level.txt
wccqcc/tools/crawl_combasic.py
wccqcc/tools/crawl_combasic_loop.sh
wccqcc/tools/crawl_expander.py
wccqcc/tools/crawl_expander_loop.sh
wccqcc/tools/update_firmkeys.py
wccqcc/tools/validate_firmkeys.py