Metadata-Version: 1.1
Name: wccqcc
Version: 0.3.3
Summary: Wikicivi WCC Qichacha
Home-page: http://wccqcc.wikicivi.com
Author: Jiao Shuai
Author-email: jiaoshuaihit@gmail.com
License: UNKNOWN
Platform: UNKNOWN
Classifier: Development Status :: 5 - Production/Stable
Classifier: Intended Audience :: Developers
Classifier: License :: OSI Approved :: MIT License
Classifier: Operating System :: OS Independent
Classifier: Programming Language :: Python
Classifier: Programming Language :: Python :: 3
Classifier: Programming Language :: Python :: 3.3
Classifier: Programming Language :: Python :: 3.4
Classifier: Programming Language :: Python :: 3.5
Classifier: Programming Language :: Python :: 3.6
